mch_oss_demo/__init__.py
mch_oss_demo/main.py
mch_oss_demo-1.2.dist-info/AUTHORS
mch_oss_demo-1.2.dist-info/LICENSE
mch_oss_demo-1.2.dist-info/METADATA
mch_oss_demo-1.2.dist-info/WHEEL
mch_oss_demo-1.2.dist-info/RECORD
