Metadata-Version: 2.3
Name: mch-oss-demo
Version: 1.2
Summary: Python library to demonstrate the MeteoSwiss open-source template.
License: BSD-3-Clause
Author: Michele Cattaneo
Author-email: michele.cattaneo@meteoswiss.ch
Requires-Python: >=3.10,<3.13
Classifier: License :: OSI Approved :: BSD License
Classifier: Programming Language :: Python :: 3
Classifier: Programming Language :: Python :: 3.10
Classifier: Programming Language :: Python :: 3.11
Classifier: Programming Language :: Python :: 3.12
